django_image_renderer-0.1.3.dist-info/DESCRIPTION.rst
django_image_renderer-0.1.3.dist-info/METADATA
django_image_renderer-0.1.3.dist-info/RECORD
django_image_renderer-0.1.3.dist-info/WHEEL
django_image_renderer-0.1.3.dist-info/metadata.json
django_image_renderer-0.1.3.dist-info/top_level.txt
renderer/__init__.py
renderer/admin.py
renderer/apps.py
renderer/models.py
renderer/tests.py
renderer/urls.py
renderer/views.py
renderer/widgets.py
renderer/migrations/0001_initial.py
renderer/migrations/__init__.py
renderer/static/renderer/admin/css/master-image-widget.css
renderer/static/renderer/admin/js/master-image-widget.js
renderer/templatetags/__init__.py
renderer/templatetags/renderer.py
