Metadata-Version: 1.1
Name: django-image-renderer
Version: 0.1.3
Summary: render image in various sizes
Home-page: https://github.com/rouk1/django-image-renderer
Author: rouk1
Author-email: matthieu.jouis@gmail.com
License: WTFPL
Platform: UNKNOWN
Classifier: Development Status :: 5 - Production/Stable
Classifier: Environment :: Web Environment
Classifier: Framework :: Django
Classifier: Intended Audience :: Developers
Classifier: Operating System :: OS Independent
Classifier: Programming Language :: Python
Classifier: Programming Language :: Python :: 3
Classifier: Topic :: Internet :: WWW/HTTP
